CHE1147_demo/__init__.py
CHE1147_demo/model.py
CHE1147_demo/train.py
che1147_demo-0.2.0.dist-info/METADATA
che1147_demo-0.2.0.dist-info/WHEEL
che1147_demo-0.2.0.dist-info/top_level.txt
che1147_demo-0.2.0.dist-info/RECORD
